{"ApprovalTime": "2015-02-27T07:21:44Z", "AutoApprovalTime": "2015-02-27T07:19:22Z", "AssignmentId": "3HWRJOOET52FYJ9TAAPBVMGBX43ESJ", "WorkerId": "anon47", "AcceptTime": "2015-02-27T07:11:41Z", "HITId": "388FBO7JZRTD1R0LCDFHEB3ZZH8NYW", "Assignment": "", "answer": {"sent_inference": ["I enjoy going sailing with my father.", "I don't like eating out at upscale places.", "The cookie was good.", "Some of the players were skillful.", "Two of the shirts were striped.", "I liked the movie.", "Sometimes the weekends were sunny.", "The student was tired or hungry."], "domain": ["training1", "training2", "cookies", "players", "clothes", "movies", "weather", "students"], "sent_manipulation": ["Bob spends a lot of time with his family.", "Bob enjoys reading restaurant reviews.", "Bob has never been to the bakery before.", "John has only seen one or two football games.", "John has no interest in fashion or clothes.", "John has always loved movies.", "Bob doesn't usually pay attention to the weather.", "Bob cares about his students and keeps in touch with them."], "language": ["English"], "manipulation_level": ["high", "low", "low", "low", "low", "high", "low", "high"], "sent_context": ["John and Bob were talking about sailing yesterday.", "John and Bob were talking about restaurants yesterday.", "A few days ago, John and Bob were talking about a particular kind of cookie at a local bakery.", "Last week, John and Bob were talking about the football game.", "Last month, Bob and John were talking about the selection of shirts at a local store.", "Yesterday, John and Bob were talking about a movie at the local theater.", "Bob and John were talking about the weather during the previous month.", "A year ago, Bob and John were talking about a  student in a class they taught."], "expt_aim": ["I have no idea"], "sent_question": ["he enjoys walking in the woods alone?", "he despises fancy restaurants?", "the cookie was not excellent?", "not all of the players were skillful?", "two but not three of the shirts were striped?", "he did not love the movie?", "the weekends were not always sunny?", "the student was not both tired and hungry?"], "scale": ["training1", "training2", "good_excellent", "all_some", "two_three", "like_love", "always_sometimes", "and_or"], "speaker": ["Bob", "Bob", "Bob", "John", "John", "John", "Bob", "Bob"], "expt_gen": ["no"], "character_thoughts": ["none"], "judgment": ["2", "2", "2", "1", "1", "2", "1", "1"]}, "AssignmentStatus": "Approved", "SubmitTime": "2015-02-27T07:14:22Z"}