{"ApprovalTime": "2015-10-16T06:21:59Z", "AutoApprovalTime": "2015-10-16T06:17:16Z", "AssignmentId": "3QAVNHZ3EM4P4TXRAWQONHCQXE9ALZ", "WorkerId": "anon21", "answers": {"data": {"scale": ["training1", "training1", "liked_loved", "good_excellent", "some_all", "memorable_unforgettable", "memorable_unforgettable", "palatable_delicious", "good_excellent", "good_excellent", "liked_loved", "palatable_delicious", "memorable_unforgettable", "palatable_delicious", "palatable_delicious", "good_excellent", "liked_loved", "liked_loved", "some_all", "good_excellent", "good_excellent", "palatable_delicious", "some_all", "some_all", "good_excellent", "memorable_unforgettable", "memorable_unforgettable", "good_excellent", "good_excellent", "liked_loved", "good_excellent", "palatable_delicious", "good_excellent", "palatable_delicious", "some_all", "some_all", "liked_loved", "palatable_delicious", "memorable_unforgettable", "some_all", "memorable_unforgettable", "liked_loved", "liked_loved", "memorable_unforgettable", "palatable_delicious", "some_all", "palatable_delicious", "palatable_delicious", "some_all", "memorable_unforgettable", "liked_loved", "memorable_unforgettable", "liked_loved", "good_excellent", "memorable_unforgettable", "memorable_unforgettable", "liked_loved", "palatable_delicious", "liked_loved", "palatable_delicious", "good_excellent", "palatable_delicious", "some_all", "palatable_delicious", "palatable_delicious", "palatable_delicious", "some_all", "memorable_unforgettable", "liked_loved", "some_all", "memorable_unforgettable", "good_excellent", "memorable_unforgettable", "liked_loved", "palatable_delicious", "memorable_unforgettable", "liked_loved", "some_all", "liked_loved", "good_excellent", "some_all", "good_excellent", "palatable_delicious", "good_excellent", "memorable_unforgettable", "some_all", "good_excellent", "good_excellent", "memorable_unforgettable", "some_all", "some_all", "some_all", "liked_loved", "some_all", "palatable_delicious", "liked_loved", "good_excellent", "memorable_unforgettable", "liked_loved", "some_all", "liked_loved", "memorable_unforgettable"], "degree": ["hi2", "low1", "hi2", "low2", "hi2", "hi2", "hi2", "hi1", "hi1", "hi2", "hi1", "hi1", "low2", "low2", "low2", "low1", "hi1", "hi1", "low1", "hi1", "hi2", "low2", "hi1", "low1", "low1", "low2", "hi1", "low1", "low2", "low2", "low1", "low1", "low2", "low1", "low1", "hi1", "low1", "hi2", "low1", "low1", "hi2", "hi2", "low2", "low1", "hi1", "hi1", "hi1", "hi2", "hi1", "low1", "hi2", "low2", "hi2", "low2", "hi1", "low2", "hi2", "low2", "low2", "low1", "hi1", "hi2", "low2", "low1", "low2", "hi1", "hi2", "hi1", "low1", "low2", "low1", "low1", "low1", "hi1", "hi2", "hi2", "low2", "low2", "low1", "hi2", "hi2", "hi2", "hi2", "hi2", "hi2", "low2", "low2", "hi1", "hi1", "hi2", "low1", "low2", "hi1", "hi1", "low1", "low2", "hi1", "hi1", "low1", "hi2", "low1", "low2"], "language": ["English"], "gender": ["male"], "manipulation_level": ["100", "20", "60", "100", "20", "20", "100", "20", "40", "20", "100", "100", "20", "20", "40", "60", "80", "20", "100", "80", "80", "60", "100", "20", "80", "40", "100", "40", "80", "100", "100", "20", "60", "80", "40", "60", "100", "80", "100", "80", "60", "80", "80", "60", "40", "40", "60", "60", "20", "80", "40", "100", "100", "20", "20", "60", "20", "80", "20", "60", "20", "100", "80", "100", "100", "80", "40", "80", "20", "20", "40", "20", "20", "60", "40", "80", "40", "60", "80", "100", "60", "40", "20", "60", "40", "100", "40", "60", "60", "100", "60", "40", "40", "80", "40", "60", "100", "40", "40", "80", "60", "80"], "expt_aim": ["opinions on ratings"], "expt_gen": ["none"], "judgment": ["1", "0", "1", "0", "0", "0", "1", "0", "0", "0", "1", "1", "0", "0", "0", "0", "1", "0", "1", "1", "1", "0", "1", "0", "0", "1", "0", "0", "0", "0", "0", "0", "0", "0", "0", "1", "0", "1", "0", "1", "0", "1", "0", "1", "0", "0", "0", "0", "0", "0", "0", "0", "1", "1", "1", "1", "0", "0", "1", "1", "0", "0", "0", "0", "0", "1", "0", "1", "1", "0", "0", "1", "1", "0", "0", "1", "0", "0", "0", "1", "1", "0", "0", "1", "0", "0", "0", "1", "0", "1", "0", "0", "0", "1", "1", "0", "1", "0", "1", "1", "0", "0"], "age": ["23"]}}, "AcceptTime": "2015-10-16T06:06:26Z", "HITId": "3OWZNK3RYLP0VWRNGTK8J2UOWTJU2L", "Assignment": "", "AssignmentStatus": "Approved", "SubmitTime": "2015-10-16T06:12:16Z"}