{"ApprovalTime": "2015-02-12T07:36:46Z", "AutoApprovalTime": "2015-02-12T07:35:15Z", "AssignmentId": "3F1567XTNW5MQ73ZAVKK880ZNLP9Q5", "WorkerId": "anon36", "AcceptTime": "2015-02-12T07:28:21Z", "HITId": "3VQTAXTYN3LUJ9RJZMDJKVXSMP0BUK", "Assignment": "", "answer": {"comparison": ["training", "training", "upper", "full", "lower", "upper", "lower", "full"], "domain": ["training1", "training2", "students", "weather", "clothes", "movies", "players", "cookies"], "scale": ["training1", "training2", "two_three", "and_or", "all_some", "good_excellent", "like_love", "always_sometimes"], "language": ["english"], "rating": ["2", "7", "4", "5", "6", "3", "6", "2"], "expt_aim": ["not sure"], "expt_gen": ["none"], "sent2": ["I really enjoy walking in the woods alone.", "I really despise fancy restaurants..", "Three of the students were tired.", "The weekend was sunny and windy.", "Some of the shirts were striped.", "He thought the movie was excellent.", "She liked the player.", "The cookies were always chocolate."], "sent1": ["I really enjoy going sailing with my father.", "I really don't like eating out at upscale places..", "Two but not three of the students were tired.", "The weekend was sunny or windy.", "Some but not all of the shirts were striped.", "He thought the movie was good but not excellent.", "She liked but didn't love the player.", "The cookies were sometimes chocolate."], "order": [[0, 1], [1, 0], [1, 2], [0, 2], [1, 0], [1, 2], [1, 0], [0, 2]]}, "AssignmentStatus": "Approved", "SubmitTime": "2015-02-12T07:30:15Z"}