{
    "ApprovalTime": "2015-04-24T19:01:59Z",
    "AutoApprovalTime": "2015-04-24T19:00:04Z",
    "AssignmentId": "3W8CV64QJ2Z9DE4WR5XQZU8Z1OZH9A",
    "WorkerId": "A3PZCD771ITFVZ",
    "AcceptTime": "2015-04-24T18:54:04Z",
    "HITId": "341YLJU21IZVM5WNMCVU0Z6DZYZI21",
    "Assignment": "",
    "answer": {
        "scale": [
            "training1",
            "training1",
            "palatable_delicious",
            "palatable_delicious",
            "liked_loved",
            "some_all",
            "good_excellent",
            "good_excellent",
            "memorable_unforgettable",
            "liked_loved",
            "some_all",
            "memorable_unforgettable"
        ],
        "degree": [
            "hi",
            "low",
            "low",
            "hi",
            "hi",
            "low",
            "hi",
            "low",
            "hi",
            "low",
            "hi",
            "low"
        ],
        "language": [
            "English"
        ],
        "expt_aim": [
            "ratings"
        ],
        "expt_gen": [
            "interesting. please post more."
        ],
        "judgment": [
            4,
            2,
            3,
            5,
            5,
            3,
            5,
            4,
            5,
            4,
            5,
            5
        ]
    },
    "AssignmentStatus": "Approved",
    "SubmitTime": "2015-04-24T18:55:04Z"
}